xarray_mongodb/__init__.py
xarray_mongodb/asyncio.py
xarray_mongodb/chunk.py
xarray_mongodb/common.py
xarray_mongodb/compat.py
xarray_mongodb/errors.py
xarray_mongodb/patch_pymongo.py
xarray_mongodb/py.typed
xarray_mongodb/sync.py
xarray_mongodb/tests/__init__.py
xarray_mongodb/tests/conftest.py
xarray_mongodb/tests/data.py
xarray_mongodb/tests/test_asyncio.py
xarray_mongodb/tests/test_pickle.py
xarray_mongodb/tests/test_pint.py
xarray_mongodb/tests/test_sync.py
xarray_mongodb-0.3.0.dist-info/LICENSE
xarray_mongodb-0.3.0.dist-info/METADATA
xarray_mongodb-0.3.0.dist-info/WHEEL
xarray_mongodb-0.3.0.dist-info/top_level.txt
xarray_mongodb-0.3.0.dist-info/RECORD
